{
  "language": "es",
  "name": "Biblia",
  "edition": "Canon y Apócrifos · SAIMAP Ecclesia",
  "levels": [
    {
      "code": "PEN",
      "name": "El Pentateuco",
      "sub": "12 módulos · Génesis a Deuteronomio",
      "color": "#8C6D41",
      "modules": [
        { "n": 1,  "title": "Génesis I — La Creación y la Caída",      "es": "Génesis I · Creación y Caída (Gén 1–4)",      "file": "pen/mod01.json" },
        { "n": 2,  "title": "Génesis II — De Adán a Babel",            "es": "Génesis II · De Adán a Babel (Gén 5–11)",     "file": "pen/mod02.json" },
        { "n": 3,  "title": "Génesis III — Abraham, la Promesa",       "es": "Génesis III · Abraham (Gén 12–25)",           "file": "pen/mod03.json" },
        { "n": 4,  "title": "Génesis IV — Jacob y José",               "es": "Génesis IV · Jacob y José (Gén 25–50)",       "file": "pen/mod04.json" },
        { "n": 5,  "title": "Éxodo I — Moisés y las Plagas",           "es": "Éxodo I · Moisés y las Plagas (Éx 1–11)",     "file": "pen/mod05.json" },
        { "n": 6,  "title": "Éxodo II — La Pascua y el Mar Rojo",      "es": "Éxodo II · Pascua y Mar Rojo (Éx 12–18)",     "file": "pen/mod06.json" },
        { "n": 7,  "title": "Éxodo III — El Sinaí y la Alianza",       "es": "Éxodo III · Sinaí y Alianza (Éx 19–40)",      "file": "pen/mod07.json" },
        { "n": 8,  "title": "Levítico — La Ley de Santidad",           "es": "Levítico · La Ley de Santidad",               "file": "pen/mod08.json" },
        { "n": 9,  "title": "Números I — La Marcha por el Desierto",   "es": "Números I · La Marcha por el Desierto",       "file": "pen/mod09.json" },
        { "n": 10, "title": "Números II — Rebeliones y Balaán",        "es": "Números II · Rebeliones y Balaán",            "file": "pen/mod10.json" },
        { "n": 11, "title": "Deuteronomio I — El Discurso de Moisés",  "es": "Deuteronomio I · El Discurso de Moisés",      "file": "pen/mod11.json" },
        { "n": 12, "title": "Deuteronomio II — La Alianza en Moab",    "es": "Deuteronomio II · Alianza en Moab",           "file": "pen/mod12.json" }
      ]
    },
    {
      "code": "HIS",
      "name": "Libros Históricos",
      "sub": "25 módulos · Josué a Macabeos — Completo",
      "color": "#B5651D",
      "modules": [
        { "n": 1,  "title": "Josué I — La Conquista de Canaán",           "es": "Josué I · La Conquista de Canaán (Jos 1–12)",    "file": "his/mod01.json" },
        { "n": 2,  "title": "Josué II — El Reparto de la Tierra",         "es": "Josué II · El Reparto de la Tierra (Jos 13–24)", "file": "his/mod02.json" },
        { "n": 3,  "title": "Jueces I — Otoniel, Aod, Débora y Gedeón",   "es": "Jueces I · Los Primeros Jueces (Jue 1–8)",       "file": "his/mod03.json" },
        { "n": 4,  "title": "Jueces II — Jefté y Sansón",                 "es": "Jueces II · Jefté y Sansón (Jue 9–21)",          "file": "his/mod04.json" },
        { "n": 5,  "title": "Rut — Lealtad en Belén",                     "es": "Rut · Lealtad en Belén (Rut 1–4)",                "file": "his/mod05.json" },
        { "n": 6,  "title": "1 Samuel I — Samuel y el Primer Rey",        "es": "1 Samuel I · Samuel y Saúl (1Sam 1–15)",          "file": "his/mod06.json" },
        { "n": 7,  "title": "1 Samuel II — David, Goliat y la Huida de Saúl", "es": "1 Samuel II · David y Saúl (1Sam 16–31)",     "file": "his/mod07.json" },
        { "n": 8,  "title": "2 Samuel I — David, Rey de Israel",          "es": "2 Samuel I · David, Rey (2Sam 1–12)",             "file": "his/mod08.json" },
        { "n": 9,  "title": "2 Samuel II — Absalón y el Ocaso de David",  "es": "2 Samuel II · Absalón (2Sam 13–24)",              "file": "his/mod09.json" },
        { "n": 10, "title": "1 Reyes I — Salomón, Sabiduría y Templo",    "es": "1 Reyes I · Salomón (1Re 1–11)",                  "file": "his/mod10.json" },
        { "n": 11, "title": "1 Reyes II — El Reino Dividido y Elías",     "es": "1 Reyes II · Elías (1Re 12–22)",                  "file": "his/mod11.json" },
        { "n": 12, "title": "2 Reyes I — Eliseo y el Reino del Norte",    "es": "2 Reyes I · Eliseo (2Re 1–17)",                   "file": "his/mod12.json" },
        { "n": 13, "title": "2 Reyes II — Judá hasta el Exilio",          "es": "2 Reyes II · Hasta el Exilio (2Re 18–25)",        "file": "his/mod13.json" },
        { "n": 14, "title": "1 Crónicas I — David, Rey y el Arca",        "es": "1 Crónicas I · David y el Arca (1Cr 10–21)",      "file": "his/mod14.json" },
        { "n": 15, "title": "1 Crónicas II — Los Preparativos del Templo", "es": "1 Crónicas II · Preparativos del Templo (1Cr 22–29)", "file": "his/mod15.json" },
        { "n": 16, "title": "2 Crónicas I — Salomón, Asá y Josafat",      "es": "2 Crónicas I · Salomón, Asá y Josafat (2Cr 1–20)", "file": "his/mod16.json" },
        { "n": 17, "title": "2 Crónicas II — Uzías, Manasés y el Decreto de Ciro", "es": "2 Crónicas II · Hasta el Exilio (2Cr 26–36)", "file": "his/mod17.json" },
        { "n": 18, "title": "Esdras — El Regreso y la Reconstrucción",    "es": "Esdras · El Regreso y la Reconstrucción",         "file": "his/mod18.json" },
        { "n": 19, "title": "Nehemías — La Reconstrucción de la Muralla", "es": "Nehemías · La Muralla de Jerusalén",              "file": "his/mod19.json" },
        { "n": 20, "title": "Tobías — El Ángel Rafael y la Familia Fiel", "es": "Tobías · El Ángel Rafael",                        "file": "his/mod20.json" },
        { "n": 21, "title": "Judit — La Viuda que Salvó a su Pueblo",     "es": "Judit · La Viuda que Salvó a su Pueblo",          "file": "his/mod21.json" },
        { "n": 22, "title": "Ester — La Reina que Salvó a su Pueblo",     "es": "Ester · La Reina que Salvó a su Pueblo",          "file": "his/mod22.json" },
        { "n": 23, "title": "1 Macabeos I — Matatías, Judas y la Purificación del Templo", "es": "1 Macabeos I · Judas Macabeo",  "file": "his/mod23.json" },
        { "n": 24, "title": "1 Macabeos II — Jonatán, Simón y el Fin de la Dinastía", "es": "1 Macabeos II · Jonatán y Simón",  "file": "his/mod24.json" },
        { "n": 25, "title": "2 Macabeos — Los Mártires y la Oración por los Difuntos", "es": "2 Macabeos · Los Mártires",       "file": "his/mod25.json" }
      ]
    },
    {
      "code": "SAP",
      "name": "Libros Sapienciales y Poéticos",
      "sub": "9 módulos · Job a Eclesiástico — Completo",
      "color": "#C79B00",
      "modules": [
        { "n": 1, "title": "Job I — La Prueba y el Lamento",             "es": "Job I · La Prueba y el Lamento (Job 1–19)",       "file": "sap/mod01.json" },
        { "n": 2, "title": "Job II — La Voz desde la Tormenta",          "es": "Job II · La Voz desde la Tormenta (Job 32–42)",   "file": "sap/mod02.json" },
        { "n": 3, "title": "Salmos I — Confianza, Alabanza y Arrepentimiento", "es": "Salmos I · Confianza y Alabanza",           "file": "sap/mod03.json" },
        { "n": 4, "title": "Salmos II — Refugio, Creación y Alabanza",   "es": "Salmos II · Refugio y Creación",                  "file": "sap/mod04.json" },
        { "n": 5, "title": "Proverbios — Sabiduría para la Vida Diaria", "es": "Proverbios · Sabiduría para la Vida Diaria",     "file": "sap/mod05.json" },
        { "n": 6, "title": "Eclesiastés — La Vanidad y el Sentido de la Vida", "es": "Eclesiastés · Vanidad y Sentido",           "file": "sap/mod06.json" },
        { "n": 7, "title": "Cantar de los Cantares — El Amor como Símbolo de la Alianza", "es": "Cantar de los Cantares · El Amor", "file": "sap/mod07.json" },
        { "n": 8, "title": "Sabiduría — La Justicia, la Muerte y el Elogio de la Sabiduría", "es": "Sabiduría · Justicia y Elogio de la Sabiduría", "file": "sap/mod08.json" },
        { "n": 9, "title": "Eclesiástico (Sirácida) — Sabiduría para la Vida Cotidiana", "es": "Eclesiástico · Sabiduría Cotidiana", "file": "sap/mod09.json" }
      ]
    },
    {
      "code": "PRO",
      "name": "Libros Proféticos",
      "sub": "17 módulos · Isaías a Joel — en curso",
      "color": "#7C4C9E",
      "modules": [
        { "n": 1, "title": "Isaías I — La Visión y el Anuncio del Mesías",         "es": "Isaías I · La Visión y el Mesías (Is 1–12)",       "file": "pro/mod01.json" },
        { "n": 2, "title": "Isaías II — Oráculos contra las Naciones y el Rey Ezequías", "es": "Isaías II · Oráculos y Ezequías (Is 13–39)", "file": "pro/mod02.json" },
        { "n": 3, "title": "Isaías III — Consolación y los Cantos del Siervo",    "es": "Isaías III · Consolación (Is 40–55)",              "file": "pro/mod03.json" },
        { "n": 4, "title": "Isaías IV — El Nuevo Cielo y la Nueva Tierra",        "es": "Isaías IV · Nuevo Cielo (Is 56–66)",               "file": "pro/mod04.json" },
        { "n": 5, "title": "Jeremías I — La Vocación y las Confesiones del Profeta", "es": "Jeremías I · Vocación y Confesiones (Jr 1–20)", "file": "pro/mod05.json" },
        { "n": 6, "title": "Jeremías II — La Alianza Nueva y el Rollo de Baruc",  "es": "Jeremías II · Alianza Nueva (Jr 21–38)",           "file": "pro/mod06.json" },
        { "n": 7, "title": "Jeremías III — La Caída de Jerusalén y el Epílogo",  "es": "Jeremías III · Caída de Jerusalén (Jr 39–52)",     "file": "pro/mod07.json" },
        { "n": 8, "title": "Lamentaciones — El Duelo por Jerusalén y la Esperanza Renovada", "es": "Lamentaciones · Duelo y Esperanza", "file": "pro/mod08.json" },
        { "n": 9, "title": "Baruc — Confesión, Sabiduría y Esperanza en el Destierro", "es": "Baruc · Confesión y Esperanza",         "file": "pro/mod09.json" },
        { "n": 10, "title": "Ezequiel I — La Visión de la Gloria y el Centinela", "es": "Ezequiel I · La Visión y el Centinela (Ez 1–11)", "file": "pro/mod10.json" },
        { "n": 11, "title": "Ezequiel II — La Responsabilidad Personal y la Ciudad Sanguinaria", "es": "Ezequiel II · Responsabilidad Personal (Ez 12–24)", "file": "pro/mod11.json" },
        { "n": 12, "title": "Ezequiel III — El Buen Pastor y el Valle de los Huesos Secos", "es": "Ezequiel III · El Buen Pastor (Ez 25–39)", "file": "pro/mod12.json" },
        { "n": 13, "title": "Ezequiel IV — El Templo Nuevo y el Río de la Vida", "es": "Ezequiel IV · Templo Nuevo (Ez 40–48)",         "file": "pro/mod13.json" },
        { "n": 14, "title": "Daniel I — La Fidelidad en Babilonia",              "es": "Daniel I · Fidelidad en Babilonia (Dn 1–6)",       "file": "pro/mod14.json" },
        { "n": 15, "title": "Daniel II — El Reino Eterno y la Sabiduría de Daniel", "es": "Daniel II · Reino Eterno (Dn 7–14)",             "file": "pro/mod15.json" },
        { "n": 16, "title": "Oseas — El Amor Fiel de Dios ante la Infidelidad de Israel", "es": "Oseas · El Amor Fiel de Dios",           "file": "pro/mod16.json" },
        { "n": 17, "title": "Joel — El Día del Señor y el Don del Espíritu",     "es": "Joel · El Día del Señor",                          "file": "pro/mod17.json" }
      ]
    },
    { "code": "EVA", "name": "Evangelios",                     "color": "#2F8A87", "locked": true, "moduleCount": 10 },
    { "code": "HCH", "name": "Hechos de los Apóstoles",        "color": "#3B6FA6", "locked": true, "moduleCount": 2 },
    { "code": "PAB", "name": "Corpus Paulino",                 "color": "#4F8B6B", "locked": true, "moduleCount": 14 },
    { "code": "CAT", "name": "Cartas Católicas",               "color": "#5B57A6", "locked": true, "moduleCount": 5 },
    { "code": "SJN", "name": "Cartas de San Juan",             "color": "#1CB0F6", "locked": true, "moduleCount": 2 },
    { "code": "JUD", "name": "Judas",                          "color": "#9C3D6B", "locked": true, "moduleCount": 1 },
    { "code": "APO", "name": "Apocalipsis",                    "color": "#C43535", "locked": true, "moduleCount": 2 },
    { "code": "APX", "name": "Textos Apócrifos",               "color": "#6B5B95", "locked": true, "moduleCount": 8 }
  ]
}
